LICENSE.txt
MANIFEST.in
README.rst
setup.py
django_erroneous.egg-info/PKG-INFO
django_erroneous.egg-info/SOURCES.txt
django_erroneous.egg-info/dependency_links.txt
django_erroneous.egg-info/not-zip-safe
django_erroneous.egg-info/requires.txt
django_erroneous.egg-info/top_level.txt
erroneous/__init__.py
erroneous/admin.py
erroneous/models.py
erroneous/setup.py
erroneous/signals.py
erroneous/migrations/0001_initial.py
erroneous/migrations/__init__.py