Metadata-Version: 1.1
Name: django-erroneous
Version: 0.2.0
Summary: django-erroneous makes it easy to collect and log Django application errors.
Home-page: http://github.org/mridang/django-erroneous
Author: Mridang Agarwalla
Author-email: mridang.agarwalla@gmail.com
License: BSD License
Download-URL: http://github.com/mridang/django-erroneous/downloads
Platform: UNKNOWN
Classifier: Environment :: Web Environment
Classifier: Intended Audience :: Developers
Classifier: License :: OSI Approved :: BSD License
Classifier: Operating System :: OS Independent
Classifier: Programming Language :: Python
Classifier: Framework :: Django
